icontract/__init__.py
icontract/_checkers.py
icontract/_decorators.py
icontract/_globals.py
icontract/_metaclass.py
icontract/_recompute.py
icontract/_represent.py
icontract/_types.py
icontract/errors.py
icontract/py.typed
icontract-2.7.2.dist-info/licenses/LICENSE.txt
icontract-2.7.2.dist-info/METADATA
icontract-2.7.2.dist-info/WHEEL
icontract-2.7.2.dist-info/top_level.txt
icontract-2.7.2.dist-info/RECORD
